natcap.rios-1.1.16-py2.7-nspkg.pth
natcap/rios/__init__.py
natcap/rios/disk_sort.py
natcap/rios/porter_core.py
natcap/rios/report_style.css
natcap/rios/rios.py
natcap/rios/rios_build_scenario_lulc.py
natcap/rios/version.py
natcap/rios/rui/__init__.py
natcap/rios/rui/base_widgets.py
natcap/rios/rui/baseflow_demo.json
natcap/rios/rui/biodiversity_demo.json
natcap/rios/rui/budget_selection.json
natcap/rios/rui/dialog-close.png
natcap/rios/rui/dialog-error.png
natcap/rios/rui/dialog-information-2.png
natcap/rios/rui/dialog-no-small.png
natcap/rios/rui/dialog-ok.png
natcap/rios/rui/dialog-warning-big.png
natcap/rios/rui/dialog-warning.png
natcap/rios/rui/dialog-yes-small.png
natcap/rios/rui/document-open.png
natcap/rios/rui/edit-undo.png
natcap/rios/rui/erosion_drinking_demo.json
natcap/rios/rui/erosion_reservoir_demo.json
natcap/rios/rui/executor.py
natcap/rios/rui/fileio.py
natcap/rios/rui/flood_mitigation_impact_demo.json
natcap/rios/rui/groundwater_recharge_demo.json
natcap/rios/rui/info.png
natcap/rios/rui/list-remove.png
natcap/rios/rui/natcap_logo.png
natcap/rios/rui/nutrient_retention_nitrogen_demo.json
natcap/rios/rui/nutrient_retention_phosphorus_demo.json
natcap/rios/rui/other1_demo.json
natcap/rios/rui/other2_demo.json
natcap/rios/rui/other3_demo.json
natcap/rios/rui/refresh.png
natcap/rios/rui/registrar.py
natcap/rios/rui/rios_ipa.json
natcap/rios/rui/rios_ipa.py
natcap/rios/rui/rios_porter.json
natcap/rios/rui/rios_porter.py
natcap/rios/rui/rui_validator.py
natcap/rios/rui/validate-fail.png
natcap/rios/rui/validate-pass.png
natcap/rios/rui/dbfpy/__init__.py
natcap/rios/rui/dbfpy/dbf.py
natcap/rios/rui/dbfpy/dbfnew.py
natcap/rios/rui/dbfpy/fields.py
natcap/rios/rui/dbfpy/header.py
natcap/rios/rui/dbfpy/record.py
natcap/rios/rui/dbfpy/utils.py
natcap/rios/rui/jsonschema/__init__.py
natcap/rios/rui/jsonschema/validator.py
natcap.rios-1.1.16.dist-info/DESCRIPTION.rst
natcap.rios-1.1.16.dist-info/METADATA
natcap.rios-1.1.16.dist-info/RECORD
natcap.rios-1.1.16.dist-info/WHEEL
natcap.rios-1.1.16.dist-info/metadata.json
natcap.rios-1.1.16.dist-info/namespace_packages.txt
natcap.rios-1.1.16.dist-info/top_level.txt
