Metadata-Version: 2.0
Name: natcap.rios
Version: 1.1.16
Summary: Resource Investment Optimization System
Home-page: https://bitbucket.org/natcap/rios
Author: Rich Sharp
Author-email: richpsharp@gmail.com
License: Copyright (c) 2015, The Natural Capital Project
Requires-Dist: gdal
Requires-Dist: numpy
Requires-Dist: pygeoprocessing (==0.3.0a7)
Requires-Dist: pyqt4
Requires-Dist: scipy (>=0.13.0)
